[
  {
    "id": 316442528,
    "node_id": "MDEwOlJlcG9zaXRvcnkzMTY0NDI1Mjg=",
    "name": "Online-book-store",
    "full_name": "danadvo/Online-book-store",
    "private": false,
    "owner": {
      "login": "danadvo",
      "id": 46192283,
      "node_id": "MDQ6VXNlcjQ2MTkyMjgz",
      "avatar_url": "https://avatars.githubusercontent.com/u/46192283?v=4",
      "gravatar_id": "",
      "url": "https://api.github.com/users/danadvo",
      "html_url": "https://github.com/danadvo",
      "followers_url": "https://api.github.com/users/danadvo/followers",
      "following_url": "https://api.github.com/users/danadvo/following{/other_user}",
      "gists_url": "https://api.github.com/users/danadvo/gists{/gist_id}",
      "starred_url": "https://api.github.com/users/danadvo/starred{/owner}{/repo}",
      "subscriptions_url": "https://api.github.com/users/danadvo/subscriptions",
      "organizations_url": "https://api.github.com/users/danadvo/orgs",
      "repos_url": "https://api.github.com/users/danadvo/repos",
      "events_url": "https://api.github.com/users/danadvo/events{/privacy}",
      "received_events_url": "https://api.github.com/users/danadvo/received_events",
      "type": "User",
      "user_view_type": "public",
      "site_admin": false
    },
    "html_url": "https://github.com/danadvo/Online-book-store",
    "description": "Implementation of simple Micro-Service framework, that represents an online book store management system with a delivery option.",
    "fork": false,
    "url": "https://api.github.com/repos/danadvo/Online-book-store",
    "forks_url": "https://api.github.com/repos/danadvo/Online-book-store/forks",
    "keys_url": "https://api.github.com/repos/danadvo/Online-book-store/keys{/key_id}",
    "collaborators_url": "https://api.github.com/repos/danadvo/Online-book-store/collaborators{/collaborator}",
    "teams_url": "https://api.github.com/repos/danadvo/Online-book-store/teams",
    "hooks_url": "https://api.github.com/repos/danadvo/Online-book-store/hooks",
    "issue_events_url": "https://api.github.com/repos/danadvo/Online-book-store/issues/events{/number}",
    "events_url": "https://api.github.com/repos/danadvo/Online-book-store/events",
    "assignees_url": "https://api.github.com/repos/danadvo/Online-book-store/assignees{/user}",
    "branches_url": "https://api.github.com/repos/danadvo/Online-book-store/branches{/branch}",
    "tags_url": "https://api.github.com/repos/danadvo/Online-book-store/tags",
    "blobs_url": "https://api.github.com/repos/danadvo/Online-book-store/git/blobs{/sha}",
    "git_tags_url": "https://api.github.com/repos/danadvo/Online-book-store/git/tags{/sha}",
    "git_refs_url": "https://api.github.com/repos/danadvo/Online-book-store/git/refs{/sha}",
    "trees_url": "https://api.github.com/repos/danadvo/Online-book-store/git/trees{/sha}",
    "statuses_url": "https://api.github.com/repos/danadvo/Online-book-store/statuses/{sha}",
    "languages_url": "https://api.github.com/repos/danadvo/Online-book-store/languages",
    "stargazers_url": "https://api.github.com/repos/danadvo/Online-book-store/stargazers",
    "contributors_url": "https://api.github.com/repos/danadvo/Online-book-store/contributors",
    "subscribers_url": "https://api.github.com/repos/danadvo/Online-book-store/subscribers",
    "subscription_url": "https://api.github.com/repos/danadvo/Online-book-store/subscription",
    "commits_url": "https://api.github.com/repos/danadvo/Online-book-store/commits{/sha}",
    "git_commits_url": "https://api.github.com/repos/danadvo/Online-book-store/git/commits{/sha}",
    "comments_url": "https://api.github.com/repos/danadvo/Online-book-store/comments{/number}",
    "issue_comment_url": "https://api.github.com/repos/danadvo/Online-book-store/issues/comments{/number}",
    "contents_url": "https://api.github.com/repos/danadvo/Online-book-store/contents/{+path}",
    "compare_url": "https://api.github.com/repos/danadvo/Online-book-store/compare/{base}...{head}",
    "merges_url": "https://api.github.com/repos/danadvo/Online-book-store/merges",
    "archive_url": "https://api.github.com/repos/danadvo/Online-book-store/{archive_format}{/ref}",
    "downloads_url": "https://api.github.com/repos/danadvo/Online-book-store/downloads",
    "issues_url": "https://api.github.com/repos/danadvo/Online-book-store/issues{/number}",
    "pulls_url": "https://api.github.com/repos/danadvo/Online-book-store/pulls{/number}",
    "milestones_url": "https://api.github.com/repos/danadvo/Online-book-store/milestones{/number}",
    "notifications_url": "https://api.github.com/repos/danadvo/Online-book-store/notifications{?since,all,participating}",
    "labels_url": "https://api.github.com/repos/danadvo/Online-book-store/labels{/name}",
    "releases_url": "https://api.github.com/repos/danadvo/Online-book-store/releases{/id}",
    "deployments_url": "https://api.github.com/repos/danadvo/Online-book-store/deployments",
    "created_at": "2020-11-27T08:26:07Z",
    "updated_at": "2020-11-28T10:30:01Z",
    "pushed_at": "2020-11-28T10:29:59Z",
    "git_url": "git://github.com/danadvo/Online-book-store.git",
    "ssh_url": "git@github.com:danadvo/Online-book-store.git",
    "clone_url": "https://github.com/danadvo/Online-book-store.git",
    "svn_url": "https://github.com/danadvo/Online-book-store",
    "homepage": "",
    "size": 36,
    "stargazers_count": 0,
    "watchers_count": 0,
    "language": "Java",
    "has_issues": true,
    "has_projects": true,
    "has_downloads": true,
    "has_wiki": true,
    "has_pages": false,
    "has_discussions": false,
    "forks_count": 0,
    "mirror_url": null,
    "archived": false,
    "disabled": false,
    "open_issues_count": 0,
    "license": null,
    "allow_forking": true,
    "is_template": false,
    "web_commit_signoff_required": false,
    "topics": [],
    "visibility": "public",
    "forks": 0,
    "open_issues": 0,
    "watchers": 0,
    "default_branch": "master",
    "permissions": {
      "admin": false,
      "maintain": false,
      "push": false,
      "triage": false,
      "pull": true
    },
    "score": 1
  }
]
